README.md
setup.py
pico_sdk/__init__.py
pico_sdk.egg-info/PKG-INFO
pico_sdk.egg-info/SOURCES.txt
pico_sdk.egg-info/dependency_links.txt
pico_sdk.egg-info/requires.txt
pico_sdk.egg-info/top_level.txt
pico_sdk/artifacts/headers/pico_sdk.h
pico_sdk/artifacts/linux-x86_64/libpico_native.so
pico_sdk/artifacts/macos-x86_64/libpico_native.dylib
pico_sdk/artifacts/windows-i686/pico_native.dll
pico_sdk/artifacts/windows-x86_64/pico_native.dll