Metadata-Version: 2.1
Name: pico-sdk
Version: 0.1.4
Summary: High performance, gap-free streaming from any Pico Technology oscilloscope
Home-page: https://github.com/meatysolutions/pico-sdk
Author: Meaty Solutions
Author-email: info@meaty.io
License: UNKNOWN
Platform: UNKNOWN
Classifier: Programming Language :: Python :: 3
Classifier: License :: OSI Approved :: MIT License
Classifier: Operating System :: OS Independent
Requires-Python: >=3.6
